Workbook
Name Slicer_Year: #N/A

Sheet Country
A1: Country | B1: Continent
A2: Afghanistan | B2: Asia
A3: Albania | B3: Europe
A4: Algeria | B4: Africa
A5: American Samoa | B5: Oceania
A6: Andorra | B6: Europe
A7: Angola | B7: Africa
A8: Anguilla | B8: North America
A9: Antarctica | B9: Antarctica
A10: Antigua and Barbuda | B10: North America
A11: Argentina | B11: South America
A12: Armenia | B12: Asia
... A248: Zambia | B248: Africa
A249: Zimbabwe

Sheet Customer_Data
A1: CustomerID | B1: FirstName | C1: LastName | D1: Gender | E1: Age | F1: Region | G1: Country | H1: City | I1: Email | J1: PhoneNumber | K1: SignupDate | L1: Year | M1: Month | N1: LastPurchaseDate | O1: TotalOrders | P1: TotalSpent | Q1: LoyaltyMember | R1: FeedbackScore | S1: AvgOrderValue
A2: 1 | B2: Damon | C2: Wilson | D2: Male | E2: 30 | F2: {=INDEX(Country!$B$3:$B$250, MATCH(TRUE, ISNUMBER(SEARCH(Country!$A$2:$A$509, Customer_Data[[#This Row],[Country]])),0 ))} -> Europe | G2: Liberia | H2: Harrisfurt | I2: samuelzavala@wiley.org | J2: +1-080-566-7627 | K2: 45576 | L2: =YEAR(Customer_Data[[#This Row],[LastPurchaseDate]]) -> 2024 | M2: =MONTH(Customer_Data[[#This Row],[LastPurchaseDate]]) -> 8 | N2: 45535 | O2: 49 | P2: 8710.89 | Q2: No | R2: 2 | S2: 177.77
A3: 2 | B3: Danny | C3: Stevens | D3: Male | E3: 33 | F3: {=INDEX(Country!$B$3:$B$250, MATCH(TRUE, ISNUMBER(SEARCH(Country!$A$2:$A$509, Customer_Data[[#This Row],[Country]])),0 ))} -> Asia | G3: Vanuatu | H3: Seanburgh | I3: johnsonbrandon@rodgers.com | J3: 249.673.1574x3454 | K3: 44924 | L3: =YEAR(Customer_Data[[#This Row],[LastPurchaseDate]]) -> 2025 | M3: =MONTH(Customer_Data[[#This Row],[LastPurchaseDate]]) -> 8 | N3: 45899 | O3: 15 | P3: 9312.97 | Q3: No | R3: 4 | S3: 620.86
A4: 3 | B4: Mario | C4: Mason | D4: Female | E4: 30 | F4: {=INDEX(Country!$B$3:$B$250, MATCH(TRUE, ISNUMBER(SEARCH(Country!$A$2:$A$509, Customer_Data[[#This Row],[Country]])),0 ))} -> Europe | G4: Uganda | H4: New Christopher | I4: walterschelsea@hotmail.com | J4: +1-803-670-4142x729 | K4: 45513 | L4: =YEAR(Customer_Data[[#This Row],[LastPurchaseDate]]) -> 2025 | M4: =MONTH(Customer_Data[[#This Row],[LastPurchaseDate]]) -> 6 | N4: 45809 | O4: 28 | P4: 5963.46 | Q4: Yes | R4: 5 | S4: 212.98
A5: 4 | B5: Gregory | C5: Morales | D5: Female | E5: 70 | F5: {=INDEX(Country!$B$3:$B$250, MATCH(TRUE, ISNUMBER(SEARCH(Country!$A$2:$A$509, Customer_Data[[#This Row],[Country]])),0 ))} -> Africa | G5: Estonia | H5: North Michael | I5: allen63@calhoun.com | J5: (913)885-1477 | K5: 45348 | L5: =YEAR(Customer_Data[[#This Row],[LastPurchaseDate]]) -> 2025 | M5: =MONTH(Customer_Data[[#This Row],[LastPurchaseDate]]) -> 9 | N5: 45916 | O5: 39 | P5: 5477.23 | Q5: No | R5: 3 | S5: 140.44
A6: 5 | B6: Bobby | C6: Bell | D6: Female | E6: 63 | F6: {=INDEX(Country!$B$3:$B$250, MATCH(TRUE, ISNUMBER(SEARCH(Country!$A$2:$A$509, Customer_Data[[#This Row],[Country]])),0 ))} -> Africa | G6: Senegal | H6: Lake Michaelfurt | I6: teresa88@gmail.com | J6: 329.278.4353x5726 | K6: 45890 | L6: =YEAR(Customer_Data[[#This Row],[LastPurchaseDate]]) -> 2025 | M6: =MONTH(Customer_Data[[#This Row],[LastPurchaseDate]]) -> 4 | N6: 45767 | O6: 38 | P6: 8668.41 | Q6: No | R6: 5 | S6: 228.12
A7: 6 | B7: Johnny | C7: Johnson | D7: Female | E7: 53 | F7: {=INDEX(Country!$B$3:$B$250, MATCH(TRUE, ISNUMBER(SEARCH(Country!$A$2:$A$509, Customer_Data[[#This Row],[Country]])),0 ))} -> South America | G7: Guinea-Bissau | H7: Port Maria | I7: barneskevin@weaver-armstrong.biz | J7: 415.767.8029 | K7: 45226 | L7: =YEAR(Customer_Data[[#This Row],[LastPurchaseDate]]) -> 2025 | M7: =MONTH(Customer_Data[[#This Row],[LastPurchaseDate]]) -> 3 | N7: 45729 | O7: 4 | P7: 1627.85 | Q7: Yes | R7: 1 | S7: 406.96
A8: 7 | B8: Alexis | C8: Parker | D8: Female | E8: 36 | F8: {=INDEX(Country!$B$3:$B$250, MATCH(TRUE, ISNUMBER(SEARCH(Country!$A$2:$A$509, Customer_Data[[#This Row],[Country]])),0 ))} -> Europe | G8: Ghana | H8: Port Nicole | I8: cherylcarrillo@gmail.com | J8: 001-769-486-0609x917 | K8: 45882 | L8: =YEAR(Customer_Data[[#This Row],[LastPurchaseDate]]) -> 2023 | M8: =MONTH(Customer_Data[[#This Row],[LastPurchaseDate]]) -> 11 | N8: 45232 | O8: 18 | P8: 1536.51 | Q8: No | R8: 1 | S8: 85.36
A9: 8 | B9: Karen | C9: Hill | D9: Female | E9: 56 | F9: {=INDEX(Country!$B$3:$B$250, MATCH(TRUE, ISNUMBER(SEARCH(Country!$A$2:$A$509, Customer_Data[[#This Row],[Country]])),0 ))} -> North America | G9: Antarctica (the territory South of 60 deg S) | H9: Henryfurt | I9: brandy44@yahoo.com | J9: +1-340-604-0301 | K9: 45107 | L9: =YEAR(Customer_Data[[#This Row],[LastPurchaseDate]]) -> 2025 | M9: =MONTH(Customer_Data[[#This Row],[LastPurchaseDate]]) -> 3 | N9: 45739 | O9: 15 | P9: 7083.1 | Q9: Yes | R9: 4 | S9: 472.21
A10: 9 | B10: Caroline | C10: Rogers | D10: Female | E10: 46 | F10: {=INDEX(Country!$B$3:$B$250, MATCH(TRUE, ISNUMBER(SEARCH(Country!$A$2:$A$509, Customer_Data[[#This Row],[Country]])),0 ))} -> Asia | G10: Chad | H10: West Leslieview | I10: juan58@gmail.com | J10: 534.379.4593 | K10: 45310 | L10: =YEAR(Customer_Data[[#This Row],[LastPurchaseDate]]) -> 2024 | M10: =MONTH(Customer_Data[[#This Row],[LastPurchaseDate]]) -> 2 | N10: 45329 | O10: 45 | P10: 4779.59 | Q10: Yes | R10: 4 | S10: 106.21
A11: 10 | B11: Lacey | C11: Miller | D11: Female | E11: 44 | F11: {=INDEX(Country!$B$3:$B$250, MATCH(TRUE, ISNUMBER(SEARCH(Country!$A$2:$A$509, Customer_Data[[#This Row],[Country]])),0 ))} -> Asia | G11: Jersey | H11: Christopherberg | I11: jose52@gmail.com | J11: +1-628-652-1347 | K11: 45505 | L11: =YEAR(Customer_Data[[#This Row],[LastPurchaseDate]]) -> 2024 | M11: =MONTH(Customer_Data[[#This Row],[LastPurchaseDate]]) -> 11 | N11: 45625 | O11: 23 | P11: 6270.48 | Q11: No | R11: 5 | S11: 272.63
A12: 11 | B12: Christina | C12: Adams | D12: Male | E12: 60 | F12: {=INDEX(Country!$B$3:$B$250, MATCH(TRUE, ISNUMBER(SEARCH(Country!$A$2:$A$509, Customer_Data[[#This Row],[Country]])),0 ))} -> Europe | G12: Ghana | H12: North Edwardberg | I12: fordhailey@acevedo.com | J12: 355-749-6152x6151 | K12: 45061 | L12: =YEAR(Customer_Data[[#This Row],[LastPurchaseDate]]) -> 2024 | M12: =MONTH(Customer_Data[[#This Row],[LastPurchaseDate]]) -> 10 | N12: 45566 | O12: 34 | P12: 6371.82 | Q12: Yes | R12: 1 | S12: 187.41
A13: 12 | B13: Donald | C13: Price | D13: Female | E13: 47 | F13: {=INDEX(Country!$B$3:$B$250, MATCH(TRUE, ISNUMBER(SEARCH(Country!$A$2:$A$509, Customer_Data[[#This Row],[Country]])),0 ))} -> Oceania | G13: Grenada | H13: New Paula | I13: chad87@gmail.com | J13: 460.504.7307 | K13: 45410 | L13: =YEAR(Customer_Data[[#This Row],[LastPurchaseDate]]) -> 2025 | M13: =MONTH(Customer_Data[[#This Row],[LastPurchaseDate]]) -> 1 | N13: 45688 | O13: 41 | P13: 5230.54 | Q13: Yes | R13: 3 | S13: 127.57
... A994: 1000 | B994: Rebecca | C994: Wong | D994: Male | E994: 45 | F994: {=INDEX(Country!$B$3:$B$250, MATCH(TRUE, ISNUMBER(SEARCH(Country!$A$2:$A$509, Customer_Data[[#This Row],[Country]])),0 ))} -> North America | G994: Monaco | H994: New Jenniferfort | I994: lpayne@hotmail.com | J994: 001-904-515-2205x9297 | K994: 45752 | L994: =YEAR(Customer_Data[[#This Row],[LastPurchaseDate]]) -> 2023 | M994: =MONTH(Customer_Data[[#This Row],[LastPurchaseDate]]) -> 11 | N994: 45252 | O994: 42 | P994: 8489.02 | Q994: No | R994: 4 | S994: 202.12

Sheet Tables and Charts
A1: Orders per Region | D1: Revenue per Region | G1: Feedback Score
A2: Regions | B2: Orders | D2: Regions | E2: Purchase | G2: Regions | H2: Average Feedback Score
A3: Africa | B3: 5666 | D3: Africa | E3: 1248314.7 | G3: Africa | H3: 3.029661
A4: Asia | B4: 4783 | D4: Asia | E4: 912691.29 | G4: Asia | H4: 3.0757576
A5: Europe | B5: 4685 | D5: Europe | E5: 969977.75 | G5: Europe | H5: 3.1105263
A6: North America | B6: 4489 | D6: North America | E6: 824438.46 | G6: North America | H6: 2.9942197
A7: Oceania | B7: 2499 | D7: Oceania | E7: 563900.35 | G7: Oceania | H7: 3.0092593
A8: South America | B8: 1882 | D8: South America | E8: 329889.26 | G8: South America | H8: 2.942029
A9: Antarctica | B9: 478 | D9: Antarctica | E9: 89753.05 | G9: Antarctica | H9: 3.1578947
A10: Grand Total | B10: 24482 | D10: Grand Total | E10: 4938964.8 | G10: Average | H10: =AVERAGE(H3:H9) -> 3.0456211
A12: Number of Purchase per Year
A13: Year/Month | B13: Orders
A14: 2024 | B14: 11527
A15: 1 | B15: 760
A16: 2 | B16: 998
A17: 3 | B17: 794
A18: 4 | B18: 840
A19: 5 | B19: 797
A20: 6 | B20: 1158
A21: 7 | B21: 1038
A22: 8 | B22: 962
A23: 9 | B23: 919
A24: 10 | B24: 1250
A25: 11 | B25: 1106
... A37: 10 | B37: 1129
A38: Grand Total | B38: 22010
A244: =COUNTA(A3:B241)/2 -> 34.5

Sheet Analysis
A1: Overview
A2: The dataset provides insights into product sales and customer feedback covering late 2023 to 2025.
A3: During this period, the product achieved a total revenue of ₱4.9 million from 24,482 products sold.
A4: The Africa region recorded the highest number of orders (5,666) and the greatest revenue (₱1.2 million), indicating strong market performance in that area.
A5: A direct relationship between orders and revenue is observed, although customer feedback in Africa remains only average compared to other regions possibly indicating that demand outweighs the satisfastion from product.
A6: Overall, the consistent purchases over the past two years demonstrates consistent product popularity and market growth.
A7: Key Insights
A8: Monthly Trends:
A9: In 2025, sales data reveals that product purchases typically decline after a strong month of sales. The months with the highest purchase volumes were:
A10: February (853 products), April (784 products), and June (696 products).
A12: Regional Insights:
A13: Antarctica achieved the highest customer feedback score despite lower sales volume, suggesting strong satisfaction from a smaller market.
... A28: Continue reinforcing successful strategies in Africa and Asia, using them as models for other underperforming markets.
