Workbook
Name Slicer_Department: #N/A

Sheet Employee_Data
A1: EmployeeID | B1: FirstName | C1: LastName | D1: Department | E1: Month | F1: Year | G1: HireDate | H1: PerformanceScore | I1: ProjectsCompleted | J1: MonthlySalary | K1: AnnualSalary
A2: 1 | B2: Natalie | C2: Perez | D2: IT | E2: =MONTH(Employee_Data[[#This Row],[HireDate]]) -> 7 | F2: =YEAR(Employee_Data[[#This Row],[HireDate]]) -> 2021 | G2: 44383 | H2: 2 | I2: 1 | J2: 59277 | K2: 711324
A3: 2 | B3: Adam | C3: Johnson | D3: IT | E3: =MONTH(Employee_Data[[#This Row],[HireDate]]) -> 11 | F3: =YEAR(Employee_Data[[#This Row],[HireDate]]) -> 2016 | G3: 42681 | H3: 3 | I3: 8 | J3: 26945 | K3: 323340
A4: 3 | B4: Helen | C4: Kirby | D4: Sales | E4: =MONTH(Employee_Data[[#This Row],[HireDate]]) -> 8 | F4: =YEAR(Employee_Data[[#This Row],[HireDate]]) -> 2018 | G4: 43326 | H4: 3 | I4: 40 | J4: 81345 | K4: 976140
A5: 4 | B5: Alexander | C5: Edwards | D5: Operations | E5: =MONTH(Employee_Data[[#This Row],[HireDate]]) -> 5 | F5: =YEAR(Employee_Data[[#This Row],[HireDate]]) -> 2023 | G5: 45060 | H5: 1 | I5: 27 | J5: 72483 | K5: 869796
A6: 5 | B6: Cynthia | C6: Lam | D6: Sales | E6: =MONTH(Employee_Data[[#This Row],[HireDate]]) -> 6 | F6: =YEAR(Employee_Data[[#This Row],[HireDate]]) -> 2021 | G6: 44366 | H6: 4 | I6: 45 | J6: 84889 | K6: 1018668
A7: 6 | B7: Sharon | C7: Shepard | D7: Operations | E7: =MONTH(Employee_Data[[#This Row],[HireDate]]) -> 2 | F7: =YEAR(Employee_Data[[#This Row],[HireDate]]) -> 2024 | G7: 45347 | H7: 5 | I7: 43 | J7: 80892 | K7: 970704
A8: 7 | B8: Elijah | C8: Boyer | D8: IT | E8: =MONTH(Employee_Data[[#This Row],[HireDate]]) -> 4 | F8: =YEAR(Employee_Data[[#This Row],[HireDate]]) -> 2024 | G8: 45408 | H8: 2 | I8: 45 | J8: 42575 | K8: 510900
A9: 8 | B9: Mark | C9: Torres | D9: HR | E9: =MONTH(Employee_Data[[#This Row],[HireDate]]) -> 2 | F9: =YEAR(Employee_Data[[#This Row],[HireDate]]) -> 2020 | G9: 43884 | H9: 2 | I9: 49 | J9: 72753 | K9: 873036
A10: 9 | B10: Paul | C10: Johnson | D10: Sales | E10: =MONTH(Employee_Data[[#This Row],[HireDate]]) -> 2 | F10: =YEAR(Employee_Data[[#This Row],[HireDate]]) -> 2023 | G10: 44982 | H10: 4 | I10: 34 | J10: 81170 | K10: 974040
A11: 10 | B11: Michael | C11: Clarke | D11: HR | E11: =MONTH(Employee_Data[[#This Row],[HireDate]]) -> 8 | F11: =YEAR(Employee_Data[[#This Row],[HireDate]]) -> 2016 | G11: 42612 | H11: 5 | I11: 2 | J11: 78501 | K11: 942012
A12: 11 | B12: Andrew | C12: Dominguez | D12: HR | E12: =MONTH(Employee_Data[[#This Row],[HireDate]]) -> 7 | F12: =YEAR(Employee_Data[[#This Row],[HireDate]]) -> 2024 | G12: 45485 | H12: 1 | I12: 19 | J12: 58271 | K12: 699252
A13: 12 | B13: Mary | C13: Carroll | D13: Sales | E13: =MONTH(Employee_Data[[#This Row],[HireDate]]) -> 6 | F13: =YEAR(Employee_Data[[#This Row],[HireDate]]) -> 2018 | G13: 43271 | H13: 5 | I13: 31 | J13: 50807 | K13: 609684
... A1001: 1000 | B1001: Natasha | C1001: Yang | D1001: HR | E1001: =MONTH(Employee_Data[[#This Row],[HireDate]]) -> 5 | F1001: =YEAR(Employee_Data[[#This Row],[HireDate]]) -> 2024 | G1001: 45413 | H1001: 5 | I1001: 46 | J1001: 74738 | K1001: 896856

Sheet Tables and Charts
A1: Tables | G1: Charts
A4: Employee Count per Year | D4: Employee Count per Department
A5: Year | B5: Employee Count | D5: Department | E5: Employee Count
A6: 2016 | B6: 101 | D6: Finance | E6: 215
A7: 2017 | B7: 109 | D7: HR | E7: 213
A8: 2018 | B8: 120 | D8: IT | E8: 201
A9: 2019 | B9: 106 | D9: Operations | E9: 186
A10: 2020 | B10: 109 | D10: Sales | E10: 185
A11: 2021 | B11: 129 | D11: Grand Total | E11: 1000
A12: 2022 | B12: 108
A13: 2023 | B13: 112 | D13: Average Salary per Dept.
A14: 2024 | B14: 96 | D14: Department | E14: Average Monthly Salary
A15: Grand Total | B15: 990 | D15: Finance | E15: 72091.572
D16: HR | E16: 75066.019
D17: IT | E17: 68618.9
A18: Yearly Performance Score | D18: Operations | E18: 69628.758
A19: Year | B19: Average Performance Score | D19: Sales | E19: 67473.978
A20: 2016 | B20: 3.0594059 | D20: Total Average | E20: =AVERAGE(E15:E19) -> 70575.846
A21: 2017 | B21: 3.0183486
A22: 2018 | B22: 3.125 | D22: Average Performance Score per Dept.
A23: 2019 | B23: 3.0849057 | D23: Department | E23: Average Performance Score
A24: 2020 | B24: 2.9541284 | D24: Finance | E24: 3.172093
A25: 2021 | B25: 3.2403101 | D25: HR | E25: 3.0187793
A26: 2022 | B26: 2.8148148 | D26: IT | E26: 3.0099502
A27: 2023 | B27: 2.9821429 | D27: Operations | E27: 2.9623656
A28: 2024 | B28: 2.875 | D28: Sales | E28: 2.9567568
D29: Total Average | E29: =AVERAGE(E24:E28) -> 3.023989
D31: Projects per Year
D32: Department | E32: Projects Completed
D33: 2016 | E33: 627
D34: 2017 | E34: 553
D35: 2018 | E35: 450
D36: 2019 | E36: 578
D37: 2020 | E37: 461
D38: 2021 | E38: 550
D39: 2022 | E39: 396
D40: 2023 | E40: 395
D41: 2024 | E41: 630
D42: Grand Total | E42: 4640

Sheet Forecasting
A1: Year | B1: Performance Score | C1: Forecast(Performance Score) | D1: Lower Confidence Bound(Performance Score) | E1: Upper Confidence Bound(Performance Score)
A2: 2016 | B2: 3.0594059
A3: 2017 | B3: 3.0183486
A4: 2018 | B4: 3.125
A5: 2019 | B5: 3.0849057
A6: 2020 | B6: 2.9541284
A7: 2021 | B7: 3.2403101
A8: 2022 | B8: 2.8148148
A9: 2023 | B9: 2.9821429
A10: 2024 | B10: 2.875 | C10: 2.875 | D10: 2.875 | E10: 2.875
A11: 2025 | C11: =_xlfn.FORECAST.ETS(A11,$B$2:$B$10,$A$2:$A$10,1,1) -> 2.9289268 | D11: =C11-_xlfn.FORECAST.ETS.CONFINT(A11,$B$2:$B$10,$A$2:$A$10,0.95,1,1) -> 2.7194748 | E11: =C11+_xlfn.FORECAST.ETS.CONFINT(A11,$B$2:$B$10,$A$2:$A$10,0.95,1,1) -> 3.1383787
A12: 2026 | C12: =_xlfn.FORECAST.ETS(A12,$B$2:$B$10,$A$2:$A$10,1,1) -> 2.8363831 | D12: =C12-_xlfn.FORECAST.ETS.CONFINT(A12,$B$2:$B$10,$A$2:$A$10,0.95,1,1) -> 2.6269302 | E12: =C12+_xlfn.FORECAST.ETS.CONFINT(A12,$B$2:$B$10,$A$2:$A$10,0.95,1,1) -> 3.045836
A13: 2027 | C13: =_xlfn.FORECAST.ETS(A13,$B$2:$B$10,$A$2:$A$10,1,1) -> 2.8857004 | D13: =C13-_xlfn.FORECAST.ETS.CONFINT(A13,$B$2:$B$10,$A$2:$A$10,0.95,1,1) -> 2.6745119 | E13: =C13+_xlfn.FORECAST.ETS.CONFINT(A13,$B$2:$B$10,$A$2:$A$10,0.95,1,1) -> 3.0968888
A14: 2028 | C14: =_xlfn.FORECAST.ETS(A14,$B$2:$B$10,$A$2:$A$10,1,1) -> 2.7931567 | D14: =C14-_xlfn.FORECAST.ETS.CONFINT(A14,$B$2:$B$10,$A$2:$A$10,0.95,1,1) -> 2.5819657 | E14: =C14+_xlfn.FORECAST.ETS.CONFINT(A14,$B$2:$B$10,$A$2:$A$10,0.95,1,1) -> 3.0043477
A15: 2029 | C15: =_xlfn.FORECAST.ETS(A15,$B$2:$B$10,$A$2:$A$10,1,1) -> 2.842474 | D15: =C15-_xlfn.FORECAST.ETS.CONFINT(A15,$B$2:$B$10,$A$2:$A$10,0.95,1,1) -> 2.629508 | E15: =C15+_xlfn.FORECAST.ETS.CONFINT(A15,$B$2:$B$10,$A$2:$A$10,0.95,1,1) -> 3.0554399
A16: 2030 | C16: =_xlfn.FORECAST.ETS(A16,$B$2:$B$10,$A$2:$A$10,1,1) -> 2.7499303 | D16: =C16-_xlfn.FORECAST.ETS.CONFINT(A16,$B$2:$B$10,$A$2:$A$10,0.95,1,1) -> 2.5369593 | E16: =C16+_xlfn.FORECAST.ETS.CONFINT(A16,$B$2:$B$10,$A$2:$A$10,0.95,1,1) -> 2.9629013
F19: Overview:
F20: Based on the chart, performance score will tend to remain around 2.5 to 3 until year 2030.
F21: Meaning, performance is stagnant but no drastic increase or decrease
F23: Recommendations:
F24: Improve on trainings, workload and increase in employee count would help improve
F25: the performance score

Sheet Correlation
A1: Year | B1: Employee Count | C1: Projects | D1: Performance Score | H1: Correlation Coefficient (r) | I1: Interpretation
A2: ='Tables and Charts'!A20 -> 2016 | B2: {='Tables and Charts'!B6:B14} -> 101 | C2: {='Tables and Charts'!E33:E41} -> 627 | D2: {='Tables and Charts'!B20:B28} -> 3.0594059 | H2: +0.70 to +1.00 | I2: Strong positive relationship
A3: ='Tables and Charts'!A21 -> 2017 | B3: 109 | C3: 553 | D3: 3.0183486 | H3: +0.40 to +0.69 | I3: Moderate positive
A4: ='Tables and Charts'!A22 -> 2018 | B4: 120 | C4: 450 | D4: 3.125 | H4: +0.10 to +0.39 | I4: Weak positive
A5: ='Tables and Charts'!A23 -> 2019 | B5: 106 | C5: 578 | D5: 3.0849057 | H5: -0.10 to +0.10 | I5: No significant correlation
A6: ='Tables and Charts'!A24 -> 2020 | B6: 109 | C6: 461 | D6: 2.9541284 | H6: -0.40 to -0.69 | I6: Moderate negative
A7: ='Tables and Charts'!A25 -> 2021 | B7: 129 | C7: 550 | D7: 3.2403101 | H7: -0.70 to -1.00 | I7: Strong negative
A8: ='Tables and Charts'!A26 -> 2022 | B8: 108 | C8: 396 | D8: 2.8148148
A9: ='Tables and Charts'!A27 -> 2023 | B9: 112 | C9: 395 | D9: 2.9821429
A10: ='Tables and Charts'!A28 -> 2024 | B10: 96 | C10: 630 | D10: 2.875
A11: 2025 | D11: =_xlfn.FORECAST.LINEAR(2025,_xlfn.ANCHORARRAY(D2),A2:A10) -> 2.9078501
A12: Correlation | B12: Correlation Coefficient (r) | C12: Interpretation | E12: Year | F12: Predicted Performance Score
A13: Project - Performance Score | B13: =CORREL(_xlfn.ANCHORARRAY(C2),_xlfn.ANCHORARRAY(D2)) -> 0.26344876 | C13: Weak Positive | E13: 2025 | F13: =_xlfn.FORECAST.LINEAR(2025,_xlfn.ANCHORARRAY(D2),A2:A10) -> 2.9078501
A14: Employee Count - Performance Score | B14: =CORREL(_xlfn.ANCHORARRAY(B2),_xlfn.ANCHORARRAY(D2)) -> 0.69674771 | C14: Strong Positive Relationship | E14: 2026 | F14: =_xlfn.FORECAST.LINEAR(2026,D2:D11,A2:A11) -> 2.8859967

Sheet Analysis
A1: Overview
A2: The dataset contains 1,000 employee performance records across the Finance, HR, IT, Operations, and Sales departments from 2016 to 2024, covering a total of 24,989 projects.
A3: The data indicates a direct relationship between project volume and performance — years with fewer completed projects generally show lower performance scores.
A4: The Finance Department leads in productivity with 5,415 projects completed and also achieved the highest average performance score of 3.17 out of 5.
A5: Employee distribution across departments is relatively even, ranging from 19% to 21%, with an overall average performance score of 3.02.
A6: Overall, the organization demonstrated stable but moderate performance throughout the period. A decline in project numbers appears to correlate with lower overall employee performance.
A10: Key Insights
A11: Performance Score Trends
A12: 2018 and 2021 marked peak performance years across all departments, with the highest average scores recorded during these periods.
A13: These years also correspond to higher employee counts (120 and 129 employees), suggesting that greater workforce availability may enhance overall output and performance.
A14: Overall Performance
A15: The overall departmental performance averages 3.02 out of 5, indicating consistent delivery but also significant room for improvement in employee efficiency and engagement.
... A30: Summary Table of Key Metrics
A31: Metric | B31: Value | C31: Observation
A32: Total Employees | B32: 1000 | C32: Evenly distributed (19–21% per department)
A33: Total Projects | B33: 24989 | C33: Stable workload over time
A34: Highest Department Score | B34: 3.17 (Finance) | C34: Consistent top performer
A35: Overall Average Score | B35: 3.02 / 5 | C35: Moderate performance level
A36: Peak Years | B36: 2018, 2021 | C36: Highest performance and employee counts
